as1170/__init__.py
as1170/driver.py
as1170-0.1.1.dist-info/METADATA
as1170-0.1.1.dist-info/WHEEL
as1170-0.1.1.dist-info/top_level.txt
as1170-0.1.1.dist-info/RECORD
