Metadata-Version: 2.2
Name: as1170
Version: 0.1.1
Summary: Library to control AS1170 LED driver via I2C on Raspberry Pi
Home-page: https://github.com/SupernovaIndustries/AS1170-Python
Author: Alessandro Cursoli
Author-email: alessandro.cursoli@supernovaindustries.it
Classifier: Programming Language :: Python :: 3
Classifier: License :: OSI Approved :: MIT License
Classifier: Operating System :: POSIX :: Linux
Requires-Python: >=3.6
Requires-Dist: smbus2
Requires-Dist: RPi.GPIO
Dynamic: author
Dynamic: author-email
Dynamic: classifier
Dynamic: description
Dynamic: description-content-type
Dynamic: home-page
Dynamic: requires-dist
Dynamic: requires-python
Dynamic: summary
